kijiji_manager/__init__.py
kijiji_manager/__main__.py
kijiji_manager/app.py
kijiji_manager/cli.py
kijiji_manager/kijijiapi.py
kijiji_manager/models.py
kijiji_manager/version.py
kijiji_manager/forms/__init__.py
kijiji_manager/forms/conversation.py
kijiji_manager/forms/login.py
kijiji_manager/forms/post.py
kijiji_manager/static/favicon.ico
kijiji_manager/static/login.css
kijiji_manager/static/style.css
kijiji_manager/static/style2.css
kijiji_manager/templates/ad.html
kijiji_manager/templates/conversation.html
kijiji_manager/templates/conversations.html
kijiji_manager/templates/error.html
kijiji_manager/templates/home.html
kijiji_manager/templates/layout.html
kijiji_manager/templates/login.html
kijiji_manager/templates/post.html
kijiji_manager/templates/post_manual.html
kijiji_manager/templates/profile.html
kijiji_manager/views/__init__.py
kijiji_manager/views/ad.py
kijiji_manager/views/json.py
kijiji_manager/views/main.py
kijiji_manager/views/user.py
kijiji_manager-0.2.4.dist-info/LICENSE
kijiji_manager-0.2.4.dist-info/METADATA
kijiji_manager-0.2.4.dist-info/WHEEL
kijiji_manager-0.2.4.dist-info/entry_points.txt
kijiji_manager-0.2.4.dist-info/top_level.txt
kijiji_manager-0.2.4.dist-info/RECORD
