Metadata-Version: 2.1
Name: kijiji-manager
Version: 0.2.4
Summary: App for viewing, posting, reposting, and deleting your Kijiji ads
Home-page: https://github.com/jackm/kijiji-manager
Author: jackm
Author-email: jackm@ehelion.com
License: MIT
Keywords: kijiji,ad,manager,reposter,automation,bot,flask
Classifier: Development Status :: 3 - Alpha
Classifier: Environment :: Web Environment
Classifier: Framework :: Flask
Classifier: Intended Audience :: End Users/Desktop
Classifier: License :: OSI Approved :: MIT License
Classifier: Operating System :: OS Independent
Classifier: Programming Language :: Python :: 3
Requires-Python: >=3.7
License-File: LICENSE
Requires-Dist: Flask (~=2.2.0)
Requires-Dist: Flask-WTF (>=1.0.1)
Requires-Dist: Flask-Login (>=0.6.0)
Requires-Dist: Flask-Executor
Requires-Dist: WTForms (>=3.0.0)
Requires-Dist: httpx (~=0.24.0)
Requires-Dist: xmltodict (>=0.11)
Requires-Dist: is-safe-url
Requires-Dist: phonenumbers
Requires-Dist: pgeocode
